{
  "sections": {
    "product_hero": {
      "type": "product-hero-homepage",
      "settings": {
        "product": "",
        "hero_image": "",
        "hero_video": "",
        "show_video_overlay": false,
        "subheading": "",
        "heading": "",
        "description": "",
        "button_text": "Buy Now",
        "secondary_button_text": "Learn More",
        "secondary_button_link": "#value-proposition",
        "show_trust_badges": false,
        "trust_icon_1": "✓",
        "trust_text_1": "",
        "trust_icon_2": "✓",
        "trust_text_2": "",
        "trust_icon_3": "✓",
        "trust_text_3": "",
        "section_width": "page-width",
        "hero_height": "85vh",
        "hero_height_custom": 85,
        "color_scheme": "scheme-1",
        "padding-block-start": 0,
        "padding-block-end": 0
      }
    },
    "value_proposition": {
      "type": "value-proposition",
      "blocks": {
        "benefit_1": {
          "type": "benefit",
          "settings": {
            "icon": "✨",
            "title": "Premium Quality",
            "description": "Thoughtfully designed with premium materials."
          }
        },
        "benefit_2": {
          "type": "benefit",
          "settings": {
            "icon": "🚀",
            "title": "Fast Shipping",
            "description": "Delivered quickly and securely to your door."
          }
        },
        "benefit_3": {
          "type": "benefit",
          "settings": {
            "icon": "💯",
            "title": "Satisfaction Guaranteed",
            "description": "We stand behind our products completely."
          }
        },
        "benefit_4": {
          "type": "benefit",
          "settings": {
            "icon": "🔒",
            "title": "Secure Checkout",
            "description": "Your information is always protected."
          }
        }
      },
      "block_order": [
        "benefit_1",
        "benefit_2",
        "benefit_3",
        "benefit_4"
      ],
      "settings": {
        "heading": "Why choose us",
        "section_width": "page-width",
        "color_scheme": "scheme-1",
        "padding-block-start": 80,
        "padding-block-end": 80
      }
    },
    "problem_solution": {
      "type": "problem-solution",
      "settings": {
        "problem_label": "The Challenge",
        "problem_heading": "You deserve better",
        "problem_text": "<p>Every day, you face challenges that hold you back. The frustration of dealing with subpar solutions. The time wasted on products that don't deliver. The feeling that there must be a better way.</p>",
        "problem_image": "",
        "solution_label": "The Solution",
        "solution_heading": "Meet the difference",
        "solution_text": "<p>Our product is designed to solve your problem with thoughtful engineering and premium materials. Experience the difference that quality and attention to detail make.</p>",
        "solution_image": "",
        "product": "",
        "cta_text": "Learn More",
        "section_width": "page-width",
        "color_scheme": "scheme-1",
        "padding-block-start": 96,
        "padding-block-end": 96
      }
    },
    "product_showcase": {
      "type": "product-showcase",
      "blocks": {},
      "settings": {
        "heading": "Designed for excellence",
        "subheading": "Every detail matters",
        "section_width": "page-width",
        "color_scheme": "scheme-1",
        "padding-block-start": 96,
        "padding-block-end": 96
      }
    },
    "social_proof": {
      "type": "testimonials",
      "blocks": {},
      "settings": {
        "heading": "Trusted by thousands",
        "subheading": "Real feedback from real customers",
        "section_width": "page-width",
        "color_scheme": "scheme-1",
        "padding-block-start": 96,
        "padding-block-end": 96
      }
    },
    "trust_guarantees": {
      "type": "trust-guarantees",
      "blocks": {
        "guarantee_1": {
          "type": "guarantee",
          "settings": {
            "icon": "🚚",
            "title": "Fast Shipping",
            "description": "Free shipping on orders over $50"
          }
        },
        "guarantee_2": {
          "type": "guarantee",
          "settings": {
            "icon": "↩️",
            "title": "Easy Returns",
            "description": "30-day money-back guarantee"
          }
        },
        "guarantee_3": {
          "type": "guarantee",
          "settings": {
            "icon": "💬",
            "title": "Support",
            "description": "We're here to help when you need us"
          }
        },
        "guarantee_4": {
          "type": "guarantee",
          "settings": {
            "icon": "🔒",
            "title": "Secure Checkout",
            "description": "Your information is always protected"
          }
        }
      },
      "block_order": [
        "guarantee_1",
        "guarantee_2",
        "guarantee_3",
        "guarantee_4"
      ],
      "settings": {
        "section_width": "page-width",
        "color_scheme": "scheme-1",
        "padding-block-start": 64,
        "padding-block-end": 64
      }
    },
    "final_cta": {
      "type": "final-cta",
      "settings": {
        "product": "",
        "subheading": "",
        "heading": "Experience the difference",
        "description": "<p>Join thousands who have made the switch to premium quality.</p>",
        "button_text": "Buy Now",
        "secondary_button_text": "",
        "secondary_button_link": "",
        "background_image": "",
        "background_video": "",
        "overlay_opacity": 40,
        "show_guarantee": true,
        "guarantee_text": "30-Day Money-Back Guarantee • Free Shipping • Secure Checkout",
        "section_width": "full-width",
        "color_scheme": "scheme-1",
        "padding-block-start": 80,
        "padding-block-end": 80
      }
    }
  },
  "order": [
    "product_hero",
    "value_proposition",
    "problem_solution",
    "product_showcase",
    "social_proof",
    "trust_guarantees",
    "final_cta"
  ]
}
